Workbook

Sheet Summary
A1: Standeliver
A2: US Stadiums & Arenas
B4: Description | D4: Stadiums - All | E4: Arenas - Private | F4: College Arenas | G4: College Arenas | I4: Total US
B5: Capacity | F5: > 10k | G5: 5k - 10k | I5: Market
B7: FACILITIES DATA
B8: Total Facilities | D8: =Stadiums!B416 -> 406 | E8: =Arenas!B542 -> 531 | F8: ='College Arenas > 10,000'!B101 -> 92 | G8: ='College Arenas 5,000-10,000'!B179 -> 171 | I8: =SUM(D8:G8) -> 1200
B9: Total Facility Capacity | D9: =Stadiums!D418 -> 13396158 | E9: =Arenas!J544 -> 4089018.3 | F9: ='College Arenas > 10,000'!I103 -> 1226573.8 | G9: ='College Arenas 5,000-10,000'!I181 -> 1143341 | I9: =SUM(D9:G9) -> 19855091
B12: LOW ATTENDANCE
B13: Low Attendance | D13: 0.3 | E13: 0.3 | F13: 0.3 | G13: 0.3 | I13: 0.3
B14: Average Participation | D14: =(0.05+0.3)/2 -> 0.175 | E14: =(0.05+0.3)/2 -> 0.175 | F14: =(0.05+0.3)/2 -> 0.175 | G14: =(0.05+0.3)/2 -> 0.175 | I14: =(0.05+0.3)/2 -> 0.175
B15: Total Transactions per Event | D15: =D9*D13*D14 -> 703298.3 | E15: =E9*E13*E14 -> 214673.46 | F15: =F9*F13*F14 -> 64395.126 | G15: =G9*G13*G14 -> 60025.402 | I15: =I9*I13*I14 -> 1042392.3
B16: Transaction Fee | D16: 4 | E16: 4 | F16: 4 | G16: 4 | I16: 4
B17: Potential Monthly Revenue | D17: =D15*D16 -> 2813193.2 | E17: =E15*E16 -> 858693.85 | F17: =F15*F16 -> 257580.51 | G17: =G15*G16 -> 240101.61 | I17: =I15*I16 -> 4169569.1
B18: Potential Annual Revenue | D18: =D17*12 -> 33758318 | E18: =E17*12 -> 10304326 | F18: =F17*12 -> 3090966.1 | G18: =G17*12 -> 2881219.3 | I18: =I17*12 -> 50034830
B21: AVERAGE ATTENDANCE
B22: Average Attendance | D22: =(0.5+0.75)/2 -> 0.625 | E22: =(0.5+0.75)/2 -> 0.625 | F22: =(0.5+0.75)/2 -> 0.625 | G22: =(0.5+0.75)/2 -> 0.625 | I22: =(0.5+0.75)/2 -> 0.625
B23: Average Participation | D23: =(0.05+0.3)/2 -> 0.175 | E23: =(0.05+0.3)/2 -> 0.175 | F23: =(0.05+0.3)/2 -> 0.175 | G23: =(0.05+0.3)/2 -> 0.175 | I23: =(0.05+0.3)/2 -> 0.175
B24: Total Transactions per Event | D24: =D9*D22*D23 -> 1465204.8 | E24: =E9*E22*E23 -> 447236.38 | F24: =F9*F22*F23 -> 134156.51 | G24: =G9*G22*G23 -> 125052.92 | I24: =I9*I22*I23 -> 2171650.6
B25: Transaction Fee | D25: 4 | E25: 4 | F25: 4 | G25: 4 | I25: 4
B26: Potential Monthly Revenue | D26: =D24*D25 -> 5860819.1 | E26: =E24*E25 -> 1788945.5 | F26: =F24*F25 -> 536626.05 | G26: =G24*G25 -> 500211.69 | I26: =I24*I25 -> 8686602.4
B27: Potential Annual Revenue | D27: =D26*12 -> 70329830 | E27: =E26*12 -> 21467346 | F27: =F26*12 -> 6439512.6 | G27: =G26*12 -> 6002540.2 | I27: =I26*12 -> 1.0423923e+08
D29: Assuming one event per month, 12 per year per facility.
D31: NFL Home games = approx 8 or 9 = .75 events per month average
D32: Major League Baseball = 81 games = 6.75 events per month average
D33: NHL Home Games = 41 = 3.42 events per month average
D34: NBA Home Games = 41 = 3.42 eventa per month average
D36: Does not include preseason or playoff games in NFL/MLB/NHL/NBA totals
D37: Does not include High School/Middle School stadiums
D38: Does not include College or High School baseball stadiums
D39: Source of Stadium/Arena data: Wikipedia

Sheet Stadiums
A1: Stadiums in the United States
A2: Capacity > 10,000
B4: The following is a list of stadiums in the United States. They are ranked by capacity, which is the maximum number of spectators the stadium can normally accommodate. All U.S. stadiums with a current
B5: capacity of 10,000 or more are included in the list. The majority of these stadiums are used for American football, either in college football or the NFL. Most of the others are Major League Baseball
B6: ballparks or Major League Soccer stadiums.
B7: https://en.wikipedia.org/wiki/List_of_U.S._stadiums_by_capacity
B9: Rows shaded in yellow indicates stadium is home to an NFL, MLB, MLS, or NWSL franchise.
B10: Rank | C10: Stadium | D10: Capacity | E10: City | F10: State | G10: Year opened | H10: Type | I10: Tenant
B11: 1 | C11: Michigan Stadium[1] | D11: 107601 | E11: Ann Arbor | F11: Michigan | G11: 1927 | H11: Football | I11: Michigan Wolverines (NCAA)
B12: 2 | C12: Beaver Stadium[2] | D12: 106572 | E12: University Park | F12: Pennsylvania | G12: 1960 | H12: Football | I12: Penn State Nittany Lions (NCAA)
B13: 3 | C13: Ohio Stadium[3] | D13: 102780 | E13: Columbus | F13: Ohio | G13: 1922 | H13: Football | I13: Ohio State Buckeyes (NCAA)
B14: 4 | C14: Kyle Field | D14: 102733 | E14: College Station | F14: Texas | G14: 1927 | H14: Football | I14: Texas A&M Aggies (NCAA)
B15: 5 | C15: Tiger Stadium[4] | D15: 102321 | E15: Baton Rouge | F15: Louisiana | G15: 1924 | H15: Football | I15: LSU Tigers (NCAA)
B16: 6 | C16: Neyland Stadium[5] | D16: 101915 | E16: Knoxville | F16: Tennessee | G16: 1921 | H16: Football | I16: Tennessee Volunteers (NCAA)
B17: 7 | C17: Darrell K Royal–Texas Memorial Stadium[6] | D17: 100119 | E17: Austin | F17: Texas | G17: 1924 | H17: Football | I17: Texas Longhorns (NCAA)
B18: 8 | C18: Bryant–Denny Stadium[7] | D18: 100077 | E18: Tuscaloosa | F18: Alabama | G18: 1929 | H18: Football | I18: Alabama Crimson Tide (NCAA)
B19: 9 | C19: Sanford Stadium[8] | D19: 92746 | E19: Athens | F19: Georgia | G19: 1929 | H19: Football | I19: Georgia Bulldogs (NCAA)
B20: 10 | C20: Rose Bowl[9] | D20: 92542 | E20: Pasadena | F20: California | G20: 1922 | H20: Football | I20: UCLA Bruins (NCAA) Rose Bowl Game (NCAA)
B21: 11 | C21: Cotton Bowl | D21: 92100 | E21: Dallas | F21: Texas | G21: 1930 | H21: Football | I21: Red River Rivalry (NCAA) State Fair Classic (NCAA)
B22: 12 | C22: Ben Hill Griffin Stadium[10] | D22: 88548 | E22: Gainesville | F22: Florida | G22: 1930 | H22: Football | I22: Florida Gators (NCAA)
... B42: 32 | C42: Highmark Stadium | D42: 71608 | E42: Orchard Park | F42: New York | G42: 1973 | H42: Football | I42: Buffalo Bills (NFL)
B43: 33 | C43: Legion Field | D43: 71594 | E43: Birmingham | F43: Alabama | G43: 1926 | H43: Football
B44: 34 | C44: Mercedes-Benz Stadium | D44: 71000 | E44: Atlanta | F44: Georgia | G44: 2017 | H44: Football, soccer | I44: Atlanta Falcons (NFL) Atlanta United FC (MLS) Peach Bowl (NCAA) SEC Championship Game (NCAA)
B45: 35 | C45: M&T Bank Stadium | D45: 70745 | E45: Baltimore | F45: Maryland | G45: 1998 | H45: Football | I45: Baltimore Ravens (NFL)
B46: 36 | C46: SoFi Stadium | D46: 70240 | E46: Inglewood | F46: California | G46: 2020 | H46: Football | I46: Los Angeles Rams (NFL) Los Angeles Chargers (NFL) LA Bowl (NCAA)
B47: 37 | C47: Husky Stadium | D47: 70083 | E47: Seattle | F47: Washington | G47: 1920 | H47: Football | I47: Washington Huskies (NCAA)
B48: 38 | C48: Kinnick Stadium | D48: 69250 | E48: Iowa City | F48: Iowa | G48: 1929 | H48: Football | I48: Iowa Hawkeyes (NCAA)
B49: 39 | C49: Raymond James Stadium | D49: 69218 | E49: Tampa | F49: Florida | G49: 1998 | H49: Football | I49: Tampa Bay Buccaneers (NFL) South Florida Bulls (NCAA) Tampa Bay Bowl (NCAA) Gasparilla Bowl (NCAA)
B50: 40 | C50: Nissan Stadium | D50: 69143 | E50: Nashville | F50: Tennessee | G50: 1999 | H50: Football | I50: Tennessee Titans (NFL) Tennessee State Tigers (NCAA) Music City Bowl (NCAA)
B51: 41 | C51: Lumen Field | D51: 68740 | E51: Seattle | F51: Washington | G51: 2002 | H51: Football, soccer | I51: Seattle Seahawks (NFL) Seattle Sounders FC (MLS) Seattle Reign FC (NWSL)
B52: 42 | C52: Levi's Stadium | D52: 68500 | E52: Santa Clara | F52: California | G52: 2014 | H52: Football | I52: San Francisco 49ers (NFL)
B53: 43 | C53: Acrisure Stadium | D53: 68400 | E53: Pittsburgh | F53: Pennsylvania | G53: 2001 | H53: Football | I53: Pittsburgh Steelers (NFL) Pittsburgh Panthers (NCAA)
B54: 44 | C54: EverBank Stadium | D54: 67814 | E54: Jacksonville | F54: Florida | G54: 1995 | H54: Football | I54: Jacksonville Jaguars (NFL) Gator Bowl (NCAA) Florida vs. Georgia Football Classic (NCAA)
B55: 45 | C55: Lincoln Financial Field | D55: 67594 | E55: Philadelphia | F55: Pennsylvania | G55: 2003 | H55: Football | I55: Philadelphia Eagles (NFL) Temple Owls (NCAA) Army–Navy Game (NCAA) (most years)
... B71: 61 | C71: Faurot Field | D71: 61620 | E71: Columbia | F71: Missouri | G71: 1926 | H71: Football | I71: Missouri Tigers (NCAA)
B72: 62 | C72: Soldier Field | D72: 61500 | E72: Chicago | F72: Illinois | G72: 1924;2003 | H72: Football, soccer | I72: Chicago Bears (NFL) Chicago Fire (MLS)
B73: 63 | C73: Scott Stadium | D73: 61500 | E73: Charlottesville | F73: Virginia | G73: 1931 | H73: Football | I73: Virginia Cavaliers (NCAA)
B74: 64 | C74: Jack Trice Stadium | D74: 61500 | E74: Ames | F74: Iowa | G74: 1975 | H74: Football | I74: Iowa State Cyclones (NCAA)
B75: 65 | C75: Yale Bowl | D75: 61446 | E75: New Haven | F75: Connecticut | G75: 1914 | H75: Football | I75: Yale Bulldogs (NCAA)
B76: 66 | C76: Ross–Ade Stadium | D76: 61441 | E76: West Lafayette | F76: Indiana | G76: 1924 | H76: Football | I76: Purdue Boilermakers (NCAA)
B77: 67 | C77: Hard Rock Stadium | D77: 64767 | E77: Miami Gardens | F77: Florida | G77: 1987 | H77: Football | I77: Miami Dolphins (NFL) Miami Hurricanes (NCAA) Orange Bowl (NCAA)
B78: 68 | C78: Davis Wade Stadium | D78: 61337 | E78: Starkville | F78: Mississippi | G78: 1914 | H78: Football | I78: Mississippi State Bulldogs (NCAA)
B79: 69 | C79: Kroger Field | D79: 61000 | E79: Lexington | F79: Kentucky | G79: 1973 | H79: Football | I79: Kentucky Wildcats (NCAA)
B80: 70 | C80: Camping World Stadium | D80: 60219 | E80: Orlando | F80: Florida | G80: 1936 | H80: Football | I80: Florida Classic (NCAA) Citrus Bowl (NCAA) Pop-Tarts Bowl (NCAA)
B81: 71 | C81: Cardinal Stadium | D81: 60800 | E81: Louisville | F81: Kentucky | G81: 1998 | H81: Football | I81: Louisville Cardinals (NCAA)
B82: 72 | C82: Memorial Stadium | D82: 60670 | E82: Champaign | F82: Illinois | G82: 1923 | H82: Football | I82: Illinois Fighting Illini (NCAA)
B83: 73 | C83: Mississippi Veterans Memorial Stadium | D83: 60492 | E83: Jackson | F83: Mississippi | G83: 1941 | H83: Football | I83: Jackson State Tigers (NCAA)
B84: 74 | C84: Jones AT&T Stadium | D84: 60454 | E84: Lubbock | F84: Texas | G84: 1947 | H84: Football | I84: Texas Tech Red Raiders (NCAA)
... B104: 94 | C104: Kenan Memorial Stadium | D104: 50500 | E104: Chapel Hill | F104: North Carolina | G104: 1927 | H104: Football | I104: North Carolina Tar Heels (NCAA)
B105: 95 | C105: Stanford Stadium | D105: 50424 | E105: Stanford | F105: California | G105: 1921;2006 | H105: Football | I105: Stanford Cardinal (NCAA)
B106: 96 | C106: Folsom Field | D106: 50183 | E106: Boulder | F106: Colorado | G106: 1924 | H106: Football | I106: Colorado Buffaloes (NCAA)
B107: 97 | C107: Bill Snyder Family Football Stadium | D107: 50000 | E107: Manhattan | F107: Kansas | G107: 1968 | H107: Football | I107: Kansas State Wildcats (NCAA)
B108: 98 | C108: Aloha Stadium | D108: 50000 | E108: Honolulu | F108: Hawaiʻi | G108: 1975 | H108: Football | I108: Closed; to be demolished
B109: 99 | C109: JMA Wireless Dome | D109: 49057 | E109: Syracuse | F109: New York | G109: 1980 | H109: Multi-purpose | I109: Syracuse Orange (NCAA)
B110: 100 | C110: Chase Field[17] | D110: 48405 | E110: Phoenix | F110: Arizona | G110: 1998 | H110: Baseball | I110: Arizona Diamondbacks (MLB) Guaranteed Rate Bowl (NCAA)
B111: 101 | C111: Choctaw Stadium | D111: 48114 | E111: Arlington | F111: Texas | G111: 1994 | H111: Multi-purpose | I111: Arlington Renegades (UFL) Dallas Jackals (MLR) North Texas SC (USL League One)
B112: 102 | C112: T-Mobile Park | D112: 47929 | E112: Seattle | F112: Washington | G112: 1999 | H112: Baseball | I112: Seattle Mariners (MLB)
B113: 103 | C113: David Booth Kansas Memorial Stadium | D113: 47233 | E113: Lawrence | F113: Kansas | G113: 1921 | H113: Football | I113: Kansas Jayhawks (NCAA)
B114: 104 | C114: Ryan Field | D114: 47130 | E114: Evanston | F114: Illinois | G114: 1996 | H114: Football | I114: Northwestern Wildcats (NCAA)
B115: 105 | C115: Protective Stadium | D115: 47100 | E115: Birmingham | F115: Alabama | G115: 2021 | H115: Football | I115: UAB Blazers (NCAA) Birmingham Legion FC (USL Championship) Birmingham Bowl (NCAA) Birmingham Stallions (UFL)
B116: 106 | C116: Rice Stadium | D116: 47000 | E116: Houston | F116: Texas | G116: 1950 | H116: Football | I116: Rice Owls (NCAA)
B117: 107 | C117: Amon G. Carter Stadium | D117: 47000 | E117: Fort Worth | F117: Texas | G117: 1930 | H117: Football | I117: TCU Horned Frogs (NCAA) Armed Forces Bowl (NCAA)
... B192: 182 | C192: ASU Stadium | D192: 26500 | E192: Montgomery | F192: Alabama | G192: 2012 | H192: Football | I192: Alabama State Hornets (NCAA)
B193: 183 | C193: Tad Gormley Stadium | D193: 26500 | E193: New Orleans | F193: Louisiana | G193: 1936 | H193: Multipurpose
B194: 184 | C194: The Glass Bowl | D194: 26038 | E194: Toledo | F194: Ohio | G194: 1937 | H194: Football | I194: Toledo Rockets (NCAA)
B195: 185 | C195: TQL Stadium | D195: 25513 | E195: Cincinnati | F195: Ohio | G195: 2021 | H195: Soccer | I195: FC Cincinnati (MLS)
B196: 186 | C196: Inter&Co Stadium | D196: 25500 | E196: Orlando | F196: Florida | G196: 2017 | H196: Soccer | I196: Orlando City SC (MLS) Orlando Pride (NWSL)
B197: 187 | C197: Ace W. Mumford Stadium | D197: 25500 | E197: Baton Rouge | F197: Louisiana | G197: 1928 | H197: Football | I197: Southern Jaguars (NCAA)
B198: 188 | C198: Hancock Whitney Stadium | D198: 25450 | E198: Mobile | F198: Alabama | G198: 2020 | H198: Football | I198: South Alabama Jaguars (NCAA) 68 Ventures Bowl (NCAA) Senior Bowl (NCAA)
B199: 189 | C199: Dix Stadium | D199: 25,319[43] | E199: Kent | F199: Ohio | G199: 1969 | H199: Football | I199: Kent State Golden Flashes (NCAA)
B200: 190 | C200: Providence Park | D200: 25218 | E200: Portland | F200: Oregon | G200: 1926 | H200: Soccer | I200: Portland Timbers (MLS) Portland Thorns (NWSL) Portland State Vikings (NCAA)
B201: 191 | C201: Washington–Grizzly Stadium | D201: 25217 | E201: Missoula | F201: Montana | G201: 1986 | H201: Football | I201: Montana Grizzlies (NCAA)
B202: 192 | C202: Maverik Stadium | D202: 25100 | E202: Logan | F202: Utah | G202: 1968 | H202: Football | I202: Utah State Aggies (NCAA)
B203: 193 | C203: UB Stadium | D203: 25013 | E203: Amherst | F203: New York | G203: 1993 | H203: Football | I203: Buffalo Bulls (NCAA)
B204: 194 | C204: Red Bull Arena | D204: 25000 | E204: Harrison | F204: New Jersey | G204: 2010 | H204: Soccer | I204: New York Red Bulls (MLS) Gotham FC (NWSL)
B205: 195 | C205: Paulson Stadium | D205: 25000 | E205: Statesboro | F205: Georgia | G205: 1984 | H205: Football | I205: Georgia Southern Eagles (NCAA)
B206: 196 | C206: Williams Stadium | D206: 25000 | E206: Lynchburg | F206: Virginia | G206: 1989 | H206: Football | I206: Liberty Flames (NCAA)
B207: 197 | C207: Cramton Bowl | D207: 25000 | E207: Montgomery | F207: Alabama | G207: 1922 | H207: Football | I207: Camellia Bowl (NCAA) Local high school teams
B208: 198 | C208: Bridgeforth Stadium | D208: 24877 | E208: Harrisonburg | F208: Virginia | G208: 1975 | H208: Football | I208: James Madison Dukes (NCAA)
B209: 199 | C209: Charles Schwab Field Omaha | D209: 24505 | E209: Omaha | F209: Nebraska | G209: 2011 | H209: Baseball | I209: Creighton Bluejays (NCAA) College World Series (NCAA)
B210: 200 | C210: Center Parc Stadium | D210: 24333 | E210: Atlanta | F210: Georgia | G210: 1996 | H210: Football | I210: Georgia State Panthers (NCAA)
B211: 201 | C211: Fred C. Yager Stadium | D211: 24286 | E211: Oxford | F211: Ohio | G211: 1983 | H211: Football | I211: Miami RedHawks (NCAA)
... B243: 233 | C243: Lower.com Field | D243: 20371 | E243: Columbus | F243: Ohio | G243: 2021 | H243: Soccer | I243: Columbus Crew (MLS)
B244: 234 | C244: Hughes Stadium | D244: 20311 | E244: Sacramento | F244: California | G244: 1928 | H244: Multi-purpose
B245: 235 | C245: America First Field | D245: 20213 | E245: Sandy | F245: Utah | G245: 2008 | H245: Soccer | I245: Real Salt Lake (MLS) Utah Royals FC (NWSL)
B246: 236 | C246: Brown Stadium | D246: 20000 | E246: Providence | F246: Rhode Island | G246: 1925 | H246: Football | I246: Brown Bears (NCAA)
B247: 237 | C247: Happy State Bank Stadium | D247: 20000 | E247: Canyon | F247: Texas | G247: 1959 | H247: Football | I247: West Texas A&M Buffaloes (NCAA) Local high school teams
B248: 238 | C248: Roy Kidd Stadium | D248: 20000 | E248: Richmond | F248: Kentucky | G248: 1969 | H248: Football | I248: Eastern Kentucky Colonels (NCAA)
B249: 239 | C249: Central Broward Park | D249: 20000 | E249: Lauderhill | F249: Florida | G249: 1969 | H249: Multipurpose | I249: Floridians FC, Fort Lauderdale Fighting Squids
B250: 240 | C250: War Memorial Stadium | D250: 20000 | E250: Wailuku | F250: Hawaii | G250: 1969 | H250: Multipurpose | I250: Local high school teams
B251: 241 | C251: FIU Stadium | D251: 20000 | E251: Miami | F251: Florida | G251: 1995 | H251: Football | I251: FIU Golden Panthers (NCAA) Miami FC (USL Championship)
B252: 242 | C252: SeatGeek Stadium | D252: 20000 | E252: Bridgeview | F252: Illinois | G252: 2006 | H252: Soccer | I252: Chicago Red Stars (NWSL) Chicago House AC (NISA) Chicago Hounds (MLR)
B253: 243 | C253: Audi Field | D253: 20000 | E253: Washington, D.C. | F253: District of Columbia | G253: 2018 | H253: Multipurpose | I253: D.C. United (MLS) Washington Spirit (NWSL) DC Defenders (UFL)
B254: 244 | C254: Historic Crew Stadium | D254: 19968 | E254: Columbus | F254: Ohio | G254: 1999 | H254: Soccer
B255: 245 | C255: Bragg Memorial Stadium | D255: 19633 | E255: Tallahassee | F255: Florida | G255: 1957 | H255: Football | I255: Florida A&M Rattlers (NCAA)
B256: 246 | C256: Eddie G. Robinson Memorial Stadium | D256: 19600 | E256: Grambling | F256: Louisiana | G256: 1983 | H256: Football | I256: Grambling State Tigers (NCAA)
B257: 247 | C257: Memorial Stadium | D257: 19468 | E257: Bakersfield | F257: California | G257: 1955 | H257: Multipurpose | I257: Bakersfield Renegades (CCCAA)
B258: 248 | C258: Mesquite Memorial Stadium | D258: 19400 | E258: Mesquite | F258: Texas | G258: 1977 | H258: Football | I258: Local high school teams
B259: 249 | C259: Allianz Field | D259: 19400 | E259: St. Paul | F259: Minnesota | G259: 2019 | H259: Soccer | I259: Minnesota United FC (MLS)
B260: 250 | C260: Dana J. Dykhouse Stadium | D260: 19340 | E260: Brookings | F260: South Dakota | G260: 2016 | H260: Football | I260: South Dakota State Jackrabbits (NCAA)
...

Sheet Arenas
A1: Stadiums in the United States
A2: Arenas
B4: List of largest municipal and privately owned arenas in the United States by seating capacity
B6: This is a list of seating capacities for sports and entertainment arenas in the United States with at least 1,000 seats. The list is composed mostly of arenas that house sports teams (basketball, ice hockey, arena soccer and arena football)
B7: and serve as indoor venues for concerts and expositions. The arenas in this table are ranked by maximum capacity. Domed stadiums (such as the Superdome in New Orleans and the U.S. Bank Stadium in Minneapolis) are excluded from this list.
B8: https://en.wikipedia.org/wiki/List_of_indoor_arenas_in_the_United_States
B9: Rows shaded in yellow indicates arena is permanent home to an NBA, NHL, or WNBA franchise.
B11: # | C11: Image | D11: Arena/venue | E11: City | F11: State | G11: Max. | H11: Basket. | I11: Hockey | J11: Average Capacity | K11: Major tenant(s) | L11: Open | M11: Area
B12: 1 | D12: Greensboro Coliseum | E12: Greensboro | F12: North Carolina | G12: 23500 | H12: 22000 | I12: 18947 | J12: =AVERAGE(G12:I12) -> 21482.333 | K12: UNC Greensboro Spartans (NCAA) | L12: 1959
B13: 2 | D13: United Center | E13: Chicago | F13: Illinois | G13: 23500 | H13: 20917 | I13: 19717 | J13: =AVERAGE(G13:I13) -> 21378 | K13: Chicago Blackhawks (NHL) Chicago Bulls (NBA) | L13: 1994 | M13: Chicagoland
B14: 3 | D14: KFC Yum! Center | E14: Louisville | F14: Kentucky | G14: 23084 | H14: 22090 | I14: 21000 | J14: =AVERAGE(G14:I14) -> 22058 | K14: Louisville Cardinals (NCAA) | L14: 2010
B15: 4 | D15: Tacoma Dome | E15: Tacoma | F15: Washington | G15: 23000 | H15: 20722 | I15: 19106 | J15: =AVERAGE(G15:I15) -> 20942.667 | L15: 1983 | M15: Seattle-Tacoma area
B16: 5 | D16: Amerant Bank Arena | E16: Sunrise | F16: Florida | G16: 22457 | H16: 20737 | I16: 19250 | J16: =AVERAGE(G16:I16) -> 20814.667 | K16: Florida Panthers (NHL) | L16: 1998 | M16: Miami metropolitan area
B17: 6 | D17: Enterprise Center | E17: St. Louis | F17: Missouri | G17: 22000 | H17: 21000 | I17: 19150 | J17: =AVERAGE(G17:I17) -> 20716.667 | K17: St. Louis Blues (NHL) | L17: 1994 | M17: Greater St. Louis
B18: 7 | D18: Amalie Arena | E18: Tampa | F18: Florida | G18: 21817 | H18: 20500 | I18: 19092 | J18: =AVERAGE(G18:I18) -> 20469.667 | K18: Tampa Bay Lightning (NHL) | L18: 1996 | M18: Tampa Bay
B19: 8 | D19: Wells Fargo Center | E19: Philadelphia | F19: Pennsylvania | G19: 21600 | H19: 20318 | I19: 19543 | J19: =AVERAGE(G19:I19) -> 20487 | K19: Philadelphia 76ers (NBA) Philadelphia Flyers (NHL) Philadelphia Wings (NLL) | L19: 1996 | M19: Greater Philadelphia
B20: 9 | D20: Lenovo Center | E20: Raleigh | F20: North Carolina | G20: 21500 | H20: 19500 | I20: 18700 | J20: =AVERAGE(G20:I20) -> 19900 | K20: Carolina Hurricanes (NHL) NC State Wolfpack (NCAA) | L20: 1999
B21: 10 | D21: Rupp Arena | E21: Lexington | F21: Kentucky | G21: 21500 | H21: 20545 | I21: 18345 | J21: =AVERAGE(G21:I21) -> 20130 | K21: Kentucky Wildcats (NCAA) | L21: 1976
B22: 11 | D22: Delta Center | E22: Salt Lake City | F22: Utah | G22: 21000 | H22: 19911 | I22: 14000 | J22: =AVERAGE(G22:I22) -> 18303.667 | K22: Utah Jazz (NBA) | L22: 1991
B23: 12 | D23: Little Caesars Arena | E23: Detroit | F23: Michigan | G23: 21000 | H23: 20491 | I23: 19515 | J23: =AVERAGE(G23:I23) -> 20335.333 | K23: Detroit Red Wings (NHL) Detroit Pistons (NBA) | L23: 2017
B24: 13 | D24: Moda Center | E24: Portland | F24: Oregon | G24: 21000 | H24: 19980 | I24: 18280 | J24: =AVERAGE(G24:I24) -> 19753.333 | K24: Portland Trail Blazers (NBA) Portland Winterhawks (WHL) | L24: 1995
B25: 14 | D25: Ball Arena | E25: Denver | F25: Colorado | G25: 21000 | H25: 19155 | I25: 18007 | J25: =AVERAGE(G25:I25) -> 19387.333 | K25: Colorado Avalanche (NHL) Denver Nuggets (NBA) Colorado Mammoth (NLL) | L25: 1999 | M25: Denver metropolitan area
B26: 15 | D26: State Farm Arena | E26: Atlanta | F26: Georgia | G26: 21000 | H26: 18047 | I26: 17624 | J26: =AVERAGE(G26:I26) -> 18890.333 | K26: Atlanta Hawks (NBA) | L26: 1999 | M26: Metro Atlanta
B27: 16 | D27: Capital One Arena | E27: Washington | F27: District of Columbia | G27: 21000 | H27: 20308 | I27: 18506 | J27: =AVERAGE(G27:I27) -> 19938 | K27: Washington Capitals (NHL) Washington Wizards (NBA) Georgetown Hoyas (NCAA) | L27: 1997 | M27: Washington–Baltimore metropolitan area
B28: 17 | D28: Madison Square Garden | E28: New York City | F28: New York | G28: 20789 | H28: 19812 | I28: 18006 | J28: =AVERAGE(G28:I28) -> 19535.667 | K28: New York Knicks (NBA) New York Rangers (NHL) St. John's Red Storm (NCAA) | L28: 1968 | M28: New York metropolitan area
B29: 18 | D29: Target Center | E29: Minneapolis | F29: Minnesota | G29: 20500 | H29: 19356 | I29: 17500 | J29: =AVERAGE(G29:I29) -> 19118.667 | K29: Minnesota Timberwolves (NBA) Minnesota Lynx (WNBA) | L29: 1990 | M29: Twin Cities
B30: 19 | D30: Spectrum Center | E30: Charlotte | F30: North Carolina | G30: 20200 | H30: 19077 | I30: 14100 | J30: =AVERAGE(G30:I30) -> 17792.333 | K30: Charlotte Hornets (NBA) | L30: 2005
B31: 20 | D31: Kaseya Center | E31: Miami | F31: Florida | G31: 20000 | H31: 19600 | I31: 14447 | J31: =AVERAGE(G31:I31) -> 18015.667 | K31: Miami Heat (NBA) | L31: 1999 | M31: Miami metropolitan area
B32: 21 | D32: American Airlines Center | E32: Dallas | F32: Texas | G32: 20000 | H32: 19200 | I32: 18532 | J32: =AVERAGE(G32:I32) -> 19244 | K32: Dallas Mavericks (NBA) Dallas Stars (NHL) | L32: 2001 | M32: Dallas–Fort Worth metroplex
B33: 22 | D33: Kia Center | E33: Orlando | F33: Florida | G33: 20000 | H33: 18846 | I33: 17353 | J33: =AVERAGE(G33:I33) -> 18733 | K33: Orlando Magic (NBA) Orlando Solar Bears (ECHL) | L33: 2010
B34: 23 | D34: Gainbridge Fieldhouse | E34: Indianapolis | F34: Indiana | G34: 20000 | H34: 18165 | I34: 15490 | J34: =AVERAGE(G34:I34) -> 17885 | K34: Indiana Pacers (NBA) Indiana Fever (WNBA) | L34: 1999
B35: 24 | D35: Bridgestone Arena | E35: Nashville | F35: Tennessee | G35: 20000 | H35: 19395 | I35: 17113 | J35: =AVERAGE(G35:I35) -> 18836 | K35: Nashville Predators (NHL) | L35: 1996
B36: 25 | D36: Nationwide Arena | E36: Columbus | F36: Ohio | G36: 20000 | H36: 19500 | I36: 18144 | J36: =AVERAGE(G36:I36) -> 19214.667 | K36: Columbus Blue Jackets (NHL) | L36: 2000
B37: 26 | D37: Oakland Arena | E37: Oakland | F37: California | G37: 20000 | H37: 19596 | I37: 17268 | J37: =AVERAGE(G37:I37) -> 18954.667 | L37: 1966 | M37: Bay Area
B38: 27 | D38: SAP Center at San Jose | E38: San Jose | F38: California | G38: 20000 | H38: 18543 | I38: 17562 | J38: =AVERAGE(G38:I38) -> 18701.667 | K38: San Jose Sharks (NHL) | L38: 1993 | M38: Bay Area
B39: 28 | D39: Crypto.com Arena | E39: Los Angeles | F39: California | G39: 20000 | H39: 18997 | I39: 18230 | J39: =AVERAGE(G39:I39) -> 19075.667 | K39: Los Angeles Kings (NHL) Los Angeles Lakers (NBA) Los Angeles Sparks (WNBA) | L39: 1999 | M39: Greater Los Angeles
B40: 29 | D40: T-Mobile Arena | E40: Paradise | F40: Nevada | G40: 20000 | H40: 18800 | I40: 17500 | J40: =AVERAGE(G40:I40) -> 18766.667 | K40: Vegas Golden Knights (NHL) | L40: 2016
B41: 30 | D41: Paycom Center | E41: Oklahoma City | F41: Oklahoma | G41: 19711 | H41: 18203 | I41: 18036 | J41: =AVERAGE(G41:I41) -> 18650 | K41: Oklahoma City Thunder (NBA) Oklahoma City Blue (NBA G League) | L41: 2002
B42: 31 | D42: TD Garden | E42: Boston | F42: Massachusetts | G42: 19580 | H42: 18624 | I42: 17565 | J42: =AVERAGE(G42:I42) -> 18589.667 | K42: Boston Bruins (NHL) Boston Celtics (NBA) | L42: 1995 | M42: Greater Boston
B43: 32 | D43: PPG Paints Arena | E43: Pittsburgh | F43: Pennsylvania | G43: 19578 | H43: 19100 | I43: 18387 | J43: =AVERAGE(G43:I43) -> 19021.667 | K43: Pittsburgh Penguins (NHL) | L43: 2010
B44: 33 | D44: FedExForum | E44: Memphis | F44: Tennessee | G44: 19500 | H44: 18119 | I44: 12633 | J44: =AVERAGE(G44:I44) -> 16750.667 | K44: Memphis Grizzlies (NBA) Memphis Tigers (NCAA) | L44: 2004 | M44: Memphis metropolitan area
B45: 34 | D45: Footprint Center | E45: Phoenix | F45: Arizona | G45: 19500 | H45: 18055 | I45: 16210 | J45: =AVERAGE(G45:I45) -> 17921.667 | K45: Phoenix Suns (NBA) Phoenix Mercury (WNBA) Arizona Rattlers (IFL) | L45: 1992 | M45: Phoenix metropolitan area
B46: 35 | D46: Prudential Center | E46: Newark | F46: New Jersey | G46: 19500 | H46: 18711 | I46: 16592 | J46: =AVERAGE(G46:I46) -> 18267.667 | K46: New Jersey Devils (NHL) Seton Hall Pirates (NCAA) | L46: 2007 | M46: New York metropolitan area
B47: 36 | D47: Chase Center | E47: San Francisco | F47: California | G47: 19500 | H47: 18064 | J47: =AVERAGE(G47:I47) -> 18782 | K47: Golden State Warriors (NBA) | L47: 2019 | M47: Bay Area
B48: 37 | D48: KeyBank Center | E48: Buffalo | F48: New York | G48: 19468 | H48: 19200 | I48: 19070 | J48: =AVERAGE(G48:I48) -> 19246 | K48: Buffalo Sabres (NHL) Buffalo Bandits (NLL) | L48: 1996
B49: 38 | D49: Rocket Mortgage FieldHouse | E49: Cleveland | F49: Ohio | G49: 19432 | H49: 19432 | I49: 18926 | J49: =AVERAGE(G49:I49) -> 19263.333 | K49: Cleveland Cavaliers (NBA) Cleveland Monsters (AHL) | L49: 1994 | M49: Cleveland-Akron
B50: 39 | D50: Xcel Energy Center | E50: St. Paul | F50: Minnesota | G50: 19355 | H50: 18600 | I50: 17954 | J50: =AVERAGE(G50:I50) -> 18636.333 | K50: Minnesota Wild (NHL) | L50: 2000 | M50: Twin Cities
B51: 40 | D51: T-Mobile Center | E51: Kansas City | F51: Missouri | G51: 19252 | H51: 18972 | I51: 17544 | J51: =AVERAGE(G51:I51) -> 18589.333 | L51: 2007
B52: 41 | D52: BOK Center | E52: Tulsa | F52: Oklahoma | G52: 19199 | H52: 17839 | I52: 17096 | J52: =AVERAGE(G52:I52) -> 18044.667 | K52: Tulsa Oilers (ECHL) | L52: 2008
B53: 42 | D53: Freedom Hall | E53: Louisville | F53: Kentucky | G53: 19169 | H53: 18865 | I53: 17062 | J53: =AVERAGE(G53:I53) -> 18365.333 | K53: Bellarmine Knights (NCAA) | L53: 1956
B54: 43 | D54: Climate Pledge Arena | E54: Seattle | F54: Washington | G54: 19125 | H54: 18600 | I54: 17400 | J54: =AVERAGE(G54:I54) -> 18375 | K54: Seattle Kraken (NHL) Seattle Storm (WNBA) Seattle Redhawks (NCAA) | L54: 1962 | M54: Seattle-Tacoma area
B55: 44 | D55: Frost Bank Center | E55: San Antonio | F55: Texas | G55: 19000 | H55: 18581 | I55: 13800 | J55: =AVERAGE(G55:I55) -> 17127 | K55: San Antonio Spurs (NBA) | L55: 2002
B56: 45 | D56: Barclays Center | E56: Brooklyn | F56: New York | G56: 19000 | H56: 17732 | I56: 15795 | J56: =AVERAGE(G56:I56) -> 17509 | K56: Brooklyn Nets (NBA) New York Liberty (WNBA) | L56: 2012 | M56: New York metropolitan area
B57: 46 | D57: Desert Diamond Arena | E57: Glendale | F57: Arizona | G57: 19000 | H57: 18300 | I57: 17125 | J57: =AVERAGE(G57:I57) -> 18141.667 | L57: 2003 | M57: Phoenix metropolitan area
B58: 47 | D58: Toyota Center | E58: Houston | F58: Texas | G58: 19000 | H58: 18055 | I58: 17800 | J58: =AVERAGE(G58:I58) -> 18285 | K58: Houston Rockets (NBA) | L58: 2003 | M58: Greater Houston
B59: 48 | D59: Simmons Bank Arena | E59: North Little Rock | F59: Arkansas | G59: 19000 | H59: 18000 | I59: 16377 | J59: =AVERAGE(G59:I59) -> 17792.333 | L59: 1999
B60: 49 | D60: Golden 1 Center | E60: Sacramento | F60: California | G60: 19000 | H60: 17608 | I60: 14632 | J60: =AVERAGE(G60:I60) -> 17080 | K60: Sacramento Kings (NBA) | L60: 2016
B61: 50 | D61: UBS Arena | E61: Elmont | F61: New York | G61: 19000 | H61: TBD | I61: 17255 | J61: =AVERAGE(G61:I61) -> 18127.5 | K61: New York Islanders (NHL) | L61: 2021 | M61: New York metropolitan area
B62: 51 | D62: Legacy Arena | E62: Birmingham | F62: Alabama | G62: 18977 | H62: 17654 | I62: 16850 | J62: =AVERAGE(G62:I62) -> 17827 | K62: Birmingham Squadron (NBA G League) | L62: 1976
B63: 52 | D63: CHI Health Center Omaha | E63: Omaha | F63: Nebraska | G63: 18975 | H63: 18320 | I63: 17100 | J63: =AVERAGE(G63:I63) -> 18131.667 | K63: Creighton Bluejays (NCAA) | L63: 2003
B64: 53 | D64: Honda Center | E64: Anaheim | F64: California | G64: 18900 | H64: 18211 | I64: 17174 | J64: =AVERAGE(G64:I64) -> 18095 | K64: Anaheim Ducks (NHL) | L64: 1993 | M64: Greater Los Angeles
B65: 54 | D65: Allstate Arena | E65: Rosemont | F65: Illinois | G65: 18500 | H65: 17500 | I65: 16692 | J65: =AVERAGE(G65:I65) -> 17564 | K65: Chicago Wolves (AHL) | L65: 1979 | M65: Chicagoland
B66: 55 | D66: Smoothie King Center | E66: New Orleans | F66: Louisiana | G66: 18500 | H66: 17188 | I66: 16500 | J66: =AVERAGE(G66:I66) -> 17396 | K66: New Orleans Pelicans (NBA) | L66: 1999 | M66: Greater New Orleans
B67: 56 | D67: The Forum | E67: Inglewood | F67: California | G67: 18000 | H67: 17505 | I67: 16005 | J67: =AVERAGE(G67:I67) -> 17170 | L67: 1967 | M67: Greater Los Angeles
B68: 57 | D68: Fiserv Forum | E68: Milwaukee | F68: Wisconsin | G68: 18000 | H68: 17500 | I68: 15178 | J68: =AVERAGE(G68:I68) -> 16892.667 | K68: Milwaukee Bucks (NBA) Marquette Golden Eagles (NCAA) | L68: 2018
B69: 58 | D69: Intuit Dome | E69: Inglewood | F69: California | G69: 18000 | H69: 18000 | J69: =AVERAGE(G69:I69) -> 18000 | K69: Los Angeles Clippers (NBA) | L69: 2024 | M69: Greater Los Angeles
B70: 59 | D70: Heritage Bank Center | E70: Cincinnati | F70: Ohio | G70: 17556 | H70: 17000 | I70: 14453 | J70: =AVERAGE(G70:I70) -> 16336.333 | K70: Cincinnati Cyclones (ECHL) | L70: 1975
B71: 60 | D71: MVP Arena | E71: Albany | F71: New York | G71: 17500 | H71: 15229 | I71: 14236 | J71: =AVERAGE(G71:I71) -> 15655 | K71: Siena Saints (NCAA) Albany FireWolves (NLL) | L71: 1990
B72: 61 | D72: MGM Grand Garden Arena | E72: Paradise | F72: Nevada | G72: 17157 | H72: 16800 | I72: 15022 | J72: =AVERAGE(G72:I72) -> 16326.333 | L72: 1993
B73: 62 | D73: Intrust Bank Arena | E73: Wichita | F73: Kansas | G73: 17000 | H73: 15004 | I73: 13450 | J73: =AVERAGE(G73:I73) -> 15151.333 | K73: Wichita Thunder (ECHL) Wichita Force (CIF) | L73: 2010
B74: 63 | D74: Wells Fargo Arena | E74: Des Moines | F74: Iowa | G74: 16980 | H74: 16110 | I74: 15181 | J74: =AVERAGE(G74:I74) -> 16090.333 | K74: Iowa Wild (AHL) Iowa Wolves (NBA G League) Iowa Barnstormers (IFL) | L74: 2005
B75: 64 | D75: XL Center | E75: Hartford | F75: Connecticut | G75: 16606 | H75: 16294 | I75: 15635 | J75: =AVERAGE(G75:I75) -> 16178.333 | K75: Hartford Wolf Pack (AHL) | L75: 1975
B76: 65 | D76: Cow Palace | E76: Daly City | F76: California | G76: 16500 | H76: 12953 | I76: 11100 | J76: =AVERAGE(G76:I76) -> 13517.667 | L76: 1941 | M76: Bay Area
B77: 66 | D77: VyStar Veterans Memorial Arena | E77: Jacksonville | F77: Florida | G77: 16301 | H77: 14091 | I77: 13141 | J77: =AVERAGE(G77:I77) -> 14511 | K77: Jacksonville Icemen (ECHL) Jacksonville Sharks (NAL) | L77: 2003
B78: 67 | D78: Pinnacle Bank Arena | E78: Lincoln | F78: Nebraska | G78: 16130 | H78: 14970 | I78: 12700 | J78: =AVERAGE(G78:I78) -> 14600 | K78: Nebraska Cornhuskers (NCAA) | L78: 2013
B79: 68 | D79: Pechanga Arena | E79: San Diego | F79: California | G79: 16100 | H79: 14500 | I79: 12920 | J79: =AVERAGE(G79:I79) -> 14506.667 | K79: San Diego Gulls (AHL) San Diego Seals (NLL) San Diego Strike Force (IFL) | L79: 1966
B80: 69 | D80: Bon Secours Wellness Arena | E80: Greenville | F80: South Carolina | G80: 15951 | H80: 14897 | I80: 13707 | J80: =AVERAGE(G80:I80) -> 14851.667 | K80: Greenville Swamp Rabbits (ECHL) | L80: 1998
B81: 70 | D81: Prairie Surf Studios | E81: Oklahoma City | F81: Oklahoma | G81: 15634 | H81: 13846 | I81: 13399 | J81: =AVERAGE(G81:I81) -> 14293 | L81: 1972
B82: 71 | D82: Mississippi Coast Coliseum | E82: Biloxi | F82: Mississippi | G82: 15000 | H82: 10200 | I82: 9150 | J82: =AVERAGE(G82:I82) -> 11450 | L82: 1977
B83: 72 | D83: Nassau Veterans Memorial Coliseum | E83: Uniondale | F83: New York | G83: 15000 | H83: 14500 | I83: 13917 | J83: =AVERAGE(G83:I83) -> 14472.333 | K83: Long Island Nets (NBA G League) New York Riptide (NLL) | L83: 1972 | M83: New York metropolitan area
B84: 73 | D84: DCU Center | E84: Worcester | F84: Massachusetts | G84: 14802 | H84: 13726 | I84: 12239 | J84: =AVERAGE(G84:I84) -> 13589 | K84: Worcester Railers (ECHL) | L84: 1982 | M84: Greater Boston
B85: 74 | D85: Arizona Veterans Memorial Coliseum | E85: Phoenix | F85: Arizona | G85: 14487 | H85: 14487 | I85: 13737 | J85: =AVERAGE(G85:I85) -> 14237 | L85: 1965 | M85: Phoenix metropolitan area
B86: 75 | D86: Dickies Arena | E86: Fort Worth | F86: Texas | G86: 14000 | H86: 13300 | I86: 12200 | J86: =AVERAGE(G86:I86) -> 13166.667 | K86: Panther City Lacrosse Club (NLL) | L86: 2019 | M86: Dallas–Fort Worth metroplex
B87: 76 | D87: Brookshire Grocery Arena | E87: Bossier City | F87: Louisiana | G87: 14400 | H87: 13000 | I87: 12440 | J87: =AVERAGE(G87:I87) -> 13280 | L87: 2000
B88: 77 | D88: Blue Cross Arena | E88: Rochester | F88: New York | G88: 14000 | H88: 12428 | I88: 11215 | J88: =AVERAGE(G88:I88) -> 12547.667 | K88: Rochester Americans (AHL) Rochester Knighthawks (NLL) | L88: 1955
B89: 78 | D89: CFG Bank Arena | E89: Baltimore | F89: Maryland | G89: 13300 | H89: 11614 | I89: 10582 | J89: =AVERAGE(G89:I89) -> 11832 | L89: 1962 | M89: Washington–Baltimore metropolitan area
B90: 79 | D90: Amica Mutual Pavilion | E90: Providence | F90: Rhode Island | G90: 14000 | H90: 12400 | I90: 11075 | J90: =AVERAGE(G90:I90) -> 12491.667 | K90: Providence Bruins (AHL) Providence Friars (NCAA) | L90: 1972 | M90: Greater Boston
B91: 80 | D91: Boardwalk Hall | E91: Atlantic City | F91: New Jersey | G91: 13800 | H91: 11100 | I91: 10900 | J91: =AVERAGE(G91:I91) -> 11933.333 | L91: 1929 | M91: Greater Philadelphia
B92: 81 | D92: Hampton Coliseum | E92: Hampton | F92: Virginia | G92: 13800 | H92: 10147 | I92: 7940 | J92: =AVERAGE(G92:I92) -> 10629 | L92: 1970 | M92: Hampton Roads
B93: 82 | D93: Norfolk Scope | E93: Norfolk | F93: Virginia | G93: 13800 | H93: 10253 | I93: 8700 | J93: =AVERAGE(G93:I93) -> 10917.667 | K93: Norfolk Admirals (ECHL) | L93: 1971 | M93: Hampton Roads
B94: 83 | D94: Long Beach Arena | E94: Long Beach | F94: California | G94: 13609 | H94: 11719 | I94: 11200 | J94: =AVERAGE(G94:I94) -> 12176 | L94: 1962 | M94: Greater Los Angeles
B95: 84 | D95: Charleston Civic Center | E95: Charleston | F95: West Virginia | G95: 13500 | H95: 12500 | I95: 10000 | J95: =AVERAGE(G95:I95) -> 12000 | L95: 1959
B96: 85 | D96: Cumberland County Crown Coliseum | E96: Fayetteville | F96: North Carolina | G96: 13500 | H96: 9564 | I96: 8920 | J96: =AVERAGE(G96:I96) -> 10661.333 | K96: Fayetteville Marksmen (SPHL) | L96: 1997
B97: 86 | D97: Fort Worth Convention Center | E97: Fort Worth | F97: Texas | G97: 13500 | H97: 13000 | I97: 11200 | J97: =AVERAGE(G97:I97) -> 12566.667 | L97: 1968 | M97: Dallas–Fort Worth metroplex
B98: 87 | D98: Richmond Coliseum | E98: Richmond | F98: Virginia | G98: 13410 | H98: 11666 | I98: 11008 | J98: =AVERAGE(G98:I98) -> 12028 | L98: 1971
B99: 88 | D99: North Charleston Coliseum | E99: North Charleston | F99: South Carolina | G99: 13295 | H99: 11475 | I99: 10568 | J99: =AVERAGE(G99:I99) -> 11779.333 | K99: South Carolina Stingrays (ECHL) Charleston Southern Buccaneers (NCAA) | L99: 1993
B100: 89 | D100: Van Andel Arena | E100: Grand Rapids | F100: Michigan | G100: 13184 | H100: 11500 | I100: 10834 | J100: =AVERAGE(G100:I100) -> 11839.333 | K100: Grand Rapids Griffins (AHL) Grand Rapids Gold (NBA G League) | L100: 1996
B101: 90 | D101: Ford Idaho Center | E101: Nampa | F101: Idaho | G101: 13100 | H101: 12279 | J101: =AVERAGE(G101:I101) -> 12689.5 | K101: Idaho Horsemen (AWFC) | L101: 1997
B102: 91 | D102: Gas South Arena | E102: Duluth | F102: Georgia | G102: 13000 | H102: 12000 | I102: 11355 | J102: =AVERAGE(G102:I102) -> 12118.333 | K102: Atlanta Gladiators (ECHL) Georgia Swarm (NLL) | L102: 2003 | M102: Metro Atlanta
B103: 92 | D103: Denny Sanford Premier Center | E103: Sioux Falls | F103: South Dakota | G103: 13000 | H103: 12400 | I103: 10678 | J103: =AVERAGE(G103:I103) -> 12026 | K103: Sioux Falls Storm (CIF) Sioux Falls Stampede (USHL) | L103: 2014
...

Sheet College Arenas > 10,000
A1: College/University Arenas
A2: Capacity > 10,000
B4: This table includes indoor arenas by seating capacity, which are owned and operated by universities and colleges and serve as home to college sports teams. Arenas with a capacity of at
B5: least 10,000 are included. Arenas which are shared by both professional and college teams, appear on the table of municipal arenas above. Domed stadiums are excluded from this list,
B6: with the exception of those which can be configured to serve as the home of major college basketball programs (i.e. the JMA Wireless Dome).
B7: https://en.wikipedia.org/wiki/List_of_indoor_arenas_in_the_United_States
B9: # | C9: Arena/venue | D9: City | E9: State | F9: Max. | G9: Basket. | H9: Hockey | I9: Average | J9: Major tenant(s) | K9: Open
B10: 1 | C10: JMA Wireless Dome | D10: Syracuse | E10: New York | F10: 49207 | G10: 35642 | I10: =AVERAGE(F10:H10) -> 42424.5 | J10: Syracuse Orange | K10: 1980
B11: 2 | C11: Dean Smith Center | D11: Chapel Hill | E11: North Carolina | F11: 21750 | G11: 21750 | I11: =AVERAGE(F11:H11) -> 21750 | J11: North Carolina Tar Heels | K11: 1986
B12: 3 | C12: Thompson–Boling Arena | D12: Knoxville | E12: Tennessee | F12: 21678 | G12: 21678 | I12: =AVERAGE(F12:H12) -> 21678 | J12: Tennessee Volunteers | K12: 1987
B13: 4 | C13: Thomas & Mack Center | D13: Paradise | E13: Nevada | F13: 19522 | G13: 18500 | H13: 16606 | I13: =AVERAGE(F13:H13) -> 18209.333 | J13: UNLV Runnin' Rebels | K13: 1983
B14: 5 | C14: Bud Walton Arena | D14: Fayetteville | E14: Arkansas | F14: 19368 | G14: 19368 | I14: =AVERAGE(F14:H14) -> 19368 | J14: Arkansas Razorbacks | K14: 1993
B15: 6 | C15: Colonial Life Arena | D15: Columbia | E15: South Carolina | F15: 19000 | G15: 18000 | I15: =AVERAGE(F15:H15) -> 18500 | J15: South Carolina Gamecocks | K15: 2002
B16: 7 | C16: Marriott Center | D16: Provo | E16: Utah | F16: 18987 | G16: 18987 | I16: =AVERAGE(F16:H16) -> 18987 | J16: BYU Cougars | K16: 1971
B17: 8 | C17: Value City Arena | D17: Columbus | E17: Ohio | F17: 18809 | G17: 18809 | H17: 17500 | I17: =AVERAGE(F17:H17) -> 18372.667 | J17: Ohio State Buckeyes | K17: 1998
B18: 9 | C18: Xfinity Center | D18: College Park | E18: Maryland | F18: 17950 | G18: 17950 | I18: =AVERAGE(F18:H18) -> 17950 | J18: Maryland Terrapins | K18: 2002
B19: 10 | C19: Kohl Center | D19: Madison | E19: Wisconsin | F19: 17230 | G19: 17230 | H19: 15359 | I19: =AVERAGE(F19:H19) -> 16606.333 | J19: Wisconsin Badgers | K19: 1998
B20: 11 | C20: Simon Skjodt Assembly Hall | D20: Bloomington | E20: Indiana | F20: 17222 | G20: 17222 | I20: =AVERAGE(F20:H20) -> 17222 | J20: Indiana Hoosiers | K20: 1971
B21: 12 | C21: Allen Fieldhouse | D21: Lawrence | E21: Kansas | F21: 16300 | G21: 16300 | I21: =AVERAGE(F21:H21) -> 16300 | J21: Kansas Jayhawks | K21: 1955
B22: 13 | C22: Save Mart Center | D22: Fresno | E22: California | F22: 16182 | G22: 15544 | H22: 14224 | I22: =AVERAGE(F22:H22) -> 15316.667 | J22: Fresno State Bulldogs | K22: 2003
B23: 14 | C23: State Farm Center | D23: Champaign | E23: Illinois | F23: 15500 | G23: 15500 | I23: =AVERAGE(F23:H23) -> 15500 | J23: Illinois Fighting Illini | K23: 1963
B24: 15 | C24: Dreamstyle Arena | D24: Albuquerque | E24: New Mexico | F24: 15411 | G24: 15411 | I24: =AVERAGE(F24:H24) -> 15411 | J24: New Mexico Lobos | K24: 1966
B25: 16 | C25: Carver–Hawkeye Arena | D25: Iowa City | E25: Iowa | F25: 15400 | G25: 15500 | I25: =AVERAGE(F25:H25) -> 15450 | J25: Iowa Hawkeyes | K25: 1983
B26: 17 | C26: Coleman Coliseum | D26: Tuscaloosa | E26: Alabama | F26: 15383 | G26: 15383 | I26: =AVERAGE(F26:H26) -> 15383 | J26: Alabama Crimson Tide | K26: 1968
B27: 18 | C27: Bryce Jordan Center | D27: University Park | E27: Pennsylvania | F27: 15261 | G27: 15261 | I27: =AVERAGE(F27:H27) -> 15261 | J27: Penn State Nittany Lions | K27: 1996
B28: 19 | C28: United Supermarkets Arena | D28: Lubbock | E28: Texas | F28: 15098 | G28: 15098 | I28: =AVERAGE(F28:H28) -> 15098 | J28: Texas Tech Red Raiders | K28: 1999
B29: 20 | C29: Mizzou Arena | D29: Columbia | E29: Missouri | F29: 15061 | G29: 15061 | I29: =AVERAGE(F29:H29) -> 15061 | J29: Missouri Tigers | K29: 2004
B30: 21 | C30: Arena-Auditorium | D30: Laramie | E30: Wyoming | F30: 15028 | G30: 15028 | I30: =AVERAGE(F30:H30) -> 15028 | J30: Wyoming Cowboys and Cowgirls | K30: 1982
B31: 22 | C31: Jon M. Huntsman Center | D31: Salt Lake City | E31: Utah | F31: 15000 | G31: 15000 | I31: =AVERAGE(F31:H31) -> 15000 | J31: Utah Utes | K31: 1969
B32: 23 | C32: Moody Center | D32: Austin | E32: Texas | F32: 15000 | G32: 10763 | I32: =AVERAGE(F32:H32) -> 12881.5 | J32: Texas Longhorns | K32: 2022
B33: 24 | C33: Mackey Arena | D33: West Lafayette | E33: Indiana | F33: 14804 | G33: 14804 | I33: =AVERAGE(F33:H33) -> 14804 | J33: Purdue Boilermakers | K33: 1967
B34: 25 | C34: Breslin Student Events Center | D34: East Lansing | E34: Michigan | F34: 14759 | G34: 14759 | I34: =AVERAGE(F34:H34) -> 14759 | J34: Michigan State Spartans | K34: 1989
B35: 26 | C35: Lawrence Joel Veterans Memorial Coliseum | D35: Winston-Salem | E35: North Carolina | F35: 14665 | G35: 14665 | H35: 14571 | I35: =AVERAGE(F35:H35) -> 14633.667 | J35: Wake Forest Demon Deacons | K35: 1989
B36: 27 | C36: McKale Center | D36: Tucson | E36: Arizona | F36: 14644 | G36: 14644 | I36: =AVERAGE(F36:H36) -> 14644 | J36: Arizona Wildcats | K36: 1973
B37: 28 | C37: Williams Arena | D37: Minneapolis | E37: Minnesota | F37: 14625 | G37: 14625 | I37: =AVERAGE(F37:H37) -> 14625 | J37: Minnesota Golden Gophers | K37: 1928
B38: 29 | C38: John Paul Jones Arena | D38: Charlottesville | E38: Virginia | F38: 14593 | G38: 14593 | I38: =AVERAGE(F38:H38) -> 14593 | J38: Virginia Cavaliers | K38: 2006
B39: 30 | C39: Hilton Coliseum | D39: Ames | E39: Iowa | F39: 14384 | G39: 14384 | I39: =AVERAGE(F39:H39) -> 14384 | J39: Iowa State Cyclones | K39: 1971
B40: 31 | C40: Memorial Gymnasium | D40: Nashville | E40: Tennessee | F40: 14316 | G40: 14316 | I40: =AVERAGE(F40:H40) -> 14316 | J40: Vanderbilt Commodores | K40: 1952
B41: 32 | C41: WVU Coliseum | D41: Morgantown | E41: West Virginia | F41: 14000 | G41: 14000 | I41: =AVERAGE(F41:H41) -> 14000 | J41: West Virginia Mountaineers | K41: 1970
B42: 33 | C42: Pauley Pavilion | D42: Los Angeles | E42: California | F42: 13800 | G42: 13800 | I42: =AVERAGE(F42:H42) -> 13800 | J42: UCLA Bruins | K42: 1965
B43: 34 | C43: Gallagher-Iba Arena | D43: Stillwater | E43: Oklahoma | F43: 13611 | G43: 13611 | I43: =AVERAGE(F43:H43) -> 13611 | J43: Oklahoma State Cowboys and Cowgirls | K43: 1938
B44: 35 | C44: Hearnes Center | D44: Columbia | E44: Missouri | F44: 13611 | G44: 13611 | I44: =AVERAGE(F44:H44) -> 13611 | J44: Missouri Tigers | K44: 1972
B45: 36 | C45: Wolstein Center | D45: Cleveland | E45: Ohio | F45: 13610 | G45: 13610 | I45: =AVERAGE(F45:H45) -> 13610 | J45: Cleveland State Vikings | K45: 1991
B46: 37 | C46: Cajundome | D46: Lafayette | E46: Louisiana | F46: 13500 | G46: 12800 | H46: 10340 | I46: =AVERAGE(F46:H46) -> 12213.333 | J46: Louisiana Ragin' Cajuns | K46: 1985
B47: 38 | C47: University of Dayton Arena | D47: Dayton | E47: Ohio | F47: 13435 | G47: 13435 | I47: =AVERAGE(F47:H47) -> 13435 | J47: Dayton Flyers | K47: 1969
B48: 39 | C48: ExtraMile Arena | D48: Boise | E48: Idaho | F48: 13390 | G48: 13390 | I48: =AVERAGE(F48:H48) -> 13390 | J48: Boise State Broncos | K48: 1982
B49: 40 | C49: Pete Maravich Assembly Center | D49: Baton Rouge | E49: Louisiana | F49: 13215 | G49: 13215 | I49: =AVERAGE(F49:H49) -> 13215 | J49: LSU Tigers | K49: 1972
B50: 41 | C50: Fifth Third Arena | D50: Cincinnati | E50: Ohio | F50: 13176 | G50: 13176 | I50: =AVERAGE(F50:H50) -> 13176 | J50: Cincinnati Bearcats | K50: 1989
B51: 42 | C51: Convocation Center | D51: Athens | E51: Ohio | F51: 13080 | G51: 13080 | I51: =AVERAGE(F51:H51) -> 13080 | J51: Ohio Bobcats | K51: 1968
B52: 43 | C52: Reed Arena | D52: College Station | E52: Texas | F52: 12989 | G52: 12989 | I52: =AVERAGE(F52:H52) -> 12989 | J52: Texas A&M Aggies | K52: 1998
B53: 44 | C53: Crisler Center | D53: Ann Arbor | E53: Michigan | F53: 12707 | G53: 12707 | I53: =AVERAGE(F53:H53) -> 12707 | J53: Michigan Wolverines | K53: 1967
B54: 45 | C54: Bramlage Coliseum | D54: Manhattan | E54: Kansas | F54: 12528 | G54: 12528 | I54: =AVERAGE(F54:H54) -> 12528 | J54: Kansas State Wildcats | K54: 1988
B55: 46 | C55: Petersen Events Center | D55: Pittsburgh | E55: Pennsylvania | F55: 12508 | G55: 12508 | I55: =AVERAGE(F55:H55) -> 12508 | J55: Pittsburgh Panthers | K55: 2002
B56: 47 | C56: Donald L. Tucker Civic Center | D56: Tallahassee | E56: Florida | F56: 12500 | G56: 12500 | H56: 9450 | I56: =AVERAGE(F56:H56) -> 11483.333 | J56: Florida State Seminoles | K56: 1981
B57: 48 | C57: Pan American Center | D57: Las Cruces | E57: New Mexico | F57: 12482 | G57: 12482 | I57: =AVERAGE(F57:H57) -> 12482 | J57: New Mexico State Aggies | K57: 1968
B58: 49 | C58: Viejas Arena | D58: San Diego | E58: California | F58: 12414 | G58: 12414 | I58: =AVERAGE(F58:H58) -> 12414 | J58: San Diego State Aztecs | K58: 1997
B59: 50 | C59: Matthew Knight Arena | D59: Eugene | E59: Oregon | F59: 12364 | G59: 12364 | I59: =AVERAGE(F59:H59) -> 12364 | J59: Oregon Ducks | K59: 2011
B60: 51 | C60: Don Haskins Center | D60: El Paso | E60: Texas | F60: 12364 | G60: 12364 | I60: =AVERAGE(F60:H60) -> 12364 | J60: UTEP Miners | K60: 1976
B61: 52 | C61: Fifth Third Arena | D61: Cincinnati | E61: Ohio | F61: 12012 | G61: 12012 | I61: =AVERAGE(F61:H61) -> 12012 | J61: Cincinnati Bearcats | K61: 1989
B62: 53 | C62: Haas Pavilion | D62: Berkeley | E62: California | F62: 11877 | G62: 11877 | I62: =AVERAGE(F62:H62) -> 11877 | J62: California Golden Bears | K62: 1933
B63: 54 | C63: Beasley Coliseum | D63: Pullman | E63: Washington | F63: 11671 | G63: 11671 | I63: =AVERAGE(F63:H63) -> 11671 | J63: Washington State Cougars | K63: 1973
B64: 55 | C64: Ralph Engelstad Arena | D64: Grand Forks | E64: North Dakota | F64: 11640 | H64: 11640 | I64: =AVERAGE(F64:H64) -> 11640 | J64: North Dakota Fighting Hawks | K64: 2001
B65: 56 | C65: Lawlor Events Center | D65: Reno | E65: Nevada | F65: 11536 | G65: 11536 | I65: =AVERAGE(F65:H65) -> 11536 | J65: Nevada Wolf Pack | K65: 1983
B66: 57 | C66: Lloyd Noble Center | D66: Norman | E66: Oklahoma | F66: 11528 | G66: 11528 | I66: =AVERAGE(F66:H66) -> 11528 | J66: Oklahoma Sooners | K66: 1973
B67: 58 | C67: Murphy Center | D67: Murfreesboro | E67: Tennessee | F67: 11520 | G67: 11520 | I67: =AVERAGE(F67:H67) -> 11520 | J67: Middle Tennessee Blue Raiders | K67: 1972
B68: 59 | C68: Dee Events Center | D68: Ogden | E68: Utah | F68: 11500 | G68: 11500 | I68: =AVERAGE(F68:H68) -> 11500 | J68: Weber State Wildcats | K68: 1977
B69: 60 | C69: Worthen Arena | D69: Muncie | E69: Indiana | F69: 11500 | G69: 11500 | I69: =AVERAGE(F69:H69) -> 11500 | J69: Ball State Cardinals | K69: 1991
B70: 61 | C70: Kaplan Arena | D70: Williamsburg | E70: Virginia | F70: 11300 | G70: 11300 | I70: =AVERAGE(F70:H70) -> 11300 | J70: William & Mary Tribe | K70: 1971
B71: 62 | C71: Walkup Skydome | D71: Flagstaff | E71: Arizona | F71: 11230 | G71: 11230 | I71: =AVERAGE(F71:H71) -> 11230 | J71: Northern Arizona Lumberjacks | K71: 1977
B72: 63 | C72: CU Events Center | D72: Boulder | E72: Colorado | F72: 11064 | G72: 11064 | I72: =AVERAGE(F72:H72) -> 11064 | J72: Colorado Buffaloes | K72: 1979
B73: 64 | C73: Great Southern Bank Arena | D73: Springfield | E73: Missouri | F73: 11000 | G73: 11000 | I73: =AVERAGE(F73:H73) -> 11000 | J73: Missouri State Bears | K73: 2008
B74: 65 | C74: McKenzie Arena | D74: Chattanooga | E74: Tennessee | F74: 10928 | G74: 10928 | I74: =AVERAGE(F74:H74) -> 10928 | J74: Chattanooga Mocs | K74: 1982
B75: 66 | C75: Montagne Center | D75: Beaumont | E75: Texas | F75: 10746 | G75: 10746 | I75: =AVERAGE(F75:H75) -> 10746 | J75: Lamar Cardinals | K75: 1984
B76: 67 | C76: Chaifetz Arena | D76: St. Louis | E76: Missouri | F76: 10600 | G76: 10600 | I76: =AVERAGE(F76:H76) -> 10600 | J76: Saint Louis Billikens | K76: 2008
... B98: 89 | C98: EagleBank Arena | D98: Fairfax | E98: Virginia | F98: 10000 | G98: 10000 | I98: =AVERAGE(F98:H98) -> 10000 | J98: George Mason Patriots | K98: 1985
B99: 90 | C99: 3M Arena at Mariucci | D99: Minneapolis | E99: Minnesota | F99: 10000 | H99: 10000 | I99: =AVERAGE(F99:H99) -> 10000 | J99: Minnesota Golden Gophers | K99: 1993
B100: 91 | C100: Convocation Center | D100: DeKalb | E100: Illinois | F100: 10000 | G100: 10000 | I100: =AVERAGE(F100:H100) -> 10000 | J100: Northern Illinois Huskies | K100: 2002
B101: 92 | C101: MSU Dome | D101: Minot | E101: North Dakota | F101: 10000 | G101: 10000 | I101: =AVERAGE(F101:H101) -> 10000 | J101: Minot State Beavers | K101: 1981
F103: Total Facility Capacity | I103: =SUM(I10:I101) -> 1226573.8
F104: Average Attendance | I104: =(0.5+0.75)/2 -> 0.625
F105: Average Participation | I105: =(0.05+0.3)/2 -> 0.175
F106: Total Transactions per Event | I106: =I103*I104*I105 -> 134156.51
F107: Transaction Fee | I107: 4
F108: Total Monthly Revenue | I108: =I106*I107 -> 536626.05
F109: Total Potential Market Revenue | I109: =I108*12 -> 6439512.6

Sheet College Arenas 5,000-10,000
A1: College/University Arenas
A2: Capacity 5,000 - 10,000
B4: This table includes indoor arenas by seating capacity, which are owned and operated by universities and colleges and serve as home to college
B5: sports teams. Arenas with a capacity of at least 5,000 are included.
B6: https://en.wikipedia.org/wiki/List_of_indoor_arenas_in_the_United_States
C8: Image | D8: Arena | E8: City | F8: State | G8: Team | H8: Conference | I8: Capacity | J8: Opened
B9: 1 | D9: Al Lawson Center | E9: Tallahassee | F9: Florida | G9: Florida A&M | H9: SWAC | I9: 9639 | J9: 2009
B10: =B9+1 -> 2 | D10: Gill Coliseum | E10: Corvallis | F10: Oregon | G10: Oregon State | H10: Pac-12 | I10: 9604 | J10: 1949
B11: =B10+1 -> 3 | D11: The Sandy and John Black Pavilion at Ole Miss | E11: Oxford | F11: Mississippi | G11: Ole Miss | H11: SEC | I11: 9500 | J11: 2016
B12: =B11+1 -> 4 | D12: Mullins Center | E12: Amherst | F12: Massachusetts | G12: Massachusetts | H12: Atlantic 10 | I12: 9493 | J12: 1993
B13: =B12+1 -> 5 | D13: Addition Financial Arena | E13: Orlando | F13: Florida | G13: UCF | H13: The American (Big 12 in 2023) | I13: 9465 | J13: 2007
B14: =B13+1 -> 6 | D14: Truist Arena | E14: Highland Heights | F14: Kentucky | G14: Northern Kentucky | H14: Horizon | I14: 9400 | J14: 2008
B15: =B14+1 -> 7 | D15: Cameron Indoor Stadium | E15: Durham | F15: North Carolina | G15: Duke | H15: ACC | I15: 9314 | J15: 1940
B16: =B15+1 -> 8 | D16: Eblen Center | E16: Cookeville | F16: Tennessee | G16: Tennessee Tech | H16: Ohio Valley | I16: 9282 | J16: 1977
B17: =B16+1 -> 9 | D17: Edmund P. Joyce Center | E17: Notre Dame | F17: Indiana | G17: Notre Dame | H17: ACC | I17: 9149 | J17: 1968
B18: =B17+1 -> 10 | D18: Dale F. Halton Arena | E18: Charlotte | F18: North Carolina | G18: Charlotte | H18: C-USA (The American in 2023) | I18: 9105 | J18: 1996
B19: =B18+1 -> 11 | D19: Hinkle Fieldhouse | E19: Indianapolis | F19: Indiana | G19: Butler | H19: Big East | I19: 9100 | J19: 1928
B20: =B19+1 -> 12 | D20: Cam Henderson Center | E20: Huntington | F20: West Virginia | G20: Marshall | H20: C-USA (Sun Belt in 2023) | I20: 9048 | J20: 1981
B21: =B20+1 -> 13 | D21: Dunn Center | E21: Clarksville | F21: Tennessee | G21: Austin Peay | H21: ASUN | I21: 9000 | J21: 1975
... B87: =B86+1 -> 79 | D87: Alumni Coliseum | E87: Richmond | F87: Kentucky | G87: Eastern Kentucky | H87: ASUN | I87: 6500 | J87: 1963
B88: =B87+1 -> 80 | D88: William J. Nicks Building | E88: Prairie View | F88: Texas | G88: Prairie View A&M | H88: SWAC | I88: 6500 | J88: 1968[3]
B89: =B88+1 -> 81 | D89: Jerry M. Hughes Athletics Center | E89: Warrensburg | F89: Missouri | G89: Central Missouri | H89: MIAA | I89: 6500 | J89: 1976
B90: =B89+1 -> 82 | D90: Frost Arena | E90: Brookings | F90: South Dakota | G90: South Dakota State | H90: Summit | I90: 6500 | J90: 1973
B91: =B90+1 -> 83 | D91: Beeghly Center | E91: Youngstown | F91: Ohio | G91: Youngstown State | H91: Horizon | I91: 6500 | J91: 1972
B92: =B91+1 -> 84 | D92: Ellis Johnson Arena | E92: Morehead | F92: Kentucky | G92: Morehead State | H92: Ohio Valley | I92: 6500 | J92: 1981
B93: =B92+1 -> 85 | D93: Tsongas Center | E93: Lowell | F93: Massachusetts | G93: UMass Lowell | H93: America East | I93: 6496 | J93: 1998
B94: =B93+1 -> 86 | D94: Munn Ice Arena | E94: East Lansing | F94: Michigan | G94: Michigan State | H94: Big Ten | I94: 6470 | J94: 1974
B95: =B94+1 -> 87 | D95: The Coliseum | E95: Carrollton | F95: Georgia | G95: West Georgia Wolves | H95: GSC | I95: 6469 | J95: 2009[5]
B96: =B95+1 -> 88 | D96: Knapp Center | E96: Des Moines | F96: Iowa | G96: Drake | H96: Missouri Valley | I96: 6424 | J96: 1992
B97: =B96+1 -> 89 | D97: Halenbeck Hall | E97: St. Cloud | F97: Minnesota | G97: St. Cloud State Huskies | H97: Northern Sun | I97: 6400 | J97: 1965
B98: =B97+1 -> 90 | D98: Millett Hall | E98: Oxford | F98: Ohio | G98: Miami (Ohio) | H98: MAC | I98: 6400 | J98: 1968
B99: =B98+1 -> 91 | D99: Memorial Athletic and Convocation Center | E99: Kent | F99: Ohio | G99: Kent State | H99: MAC | I99: 6327 | J99: 1950
B100: =B99+1 -> 92 | D100: Alex G. Spanos Center | E100: Stockton | F100: California | G100: Pacific | H100: West Coast | I100: 6150 | J100: 1981
B101: =B100+1 -> 93 | D101: Agganis Arena | E101: Boston | F101: Massachusetts | G101: Boston University men | H101: Hockey East | I101: 6150 | J101: 2005
B102: =B101+1 -> 94 | D102: Freedom Hall Civic Center | E102: Johnson City | F102: Tennessee | G102: East Tennessee State | H102: Southern | I102: 6149 | J102: 1974
B103: =B102+1 -> 95 | D103: Winthrop Coliseum | E103: Rock Hill | F103: South Carolina | G103: Winthrop | H103: Big South | I103: 6100 | J103: 1982
B104: =B103+1 -> 96 | D104: Alumni Arena | E104: Amherst | F104: New York | G104: Buffalo | H104: MAC | I104: 6100 | J104: 1982
B105: =B104+1 -> 97 | D105: Bernard Johnson Coliseum | E105: Huntsville | F105: Texas | G105: Sam Houston | H105: WAC (C-USA in 2023) | I105: 6100 | J105: 1976
B106: =B105+1 -> 98 | D106: Pegula Ice Arena | E106: University Park | F106: Pennsylvania | G106: Penn State men & women | H106: Big Ten (men) CHA (women) | I106: 6000 | J106: 2013
B107: =B106+1 -> 99 | D107: Stabler Arena | E107: Bethlehem | F107: Pennsylvania | G107: Lehigh | H107: Patriot | I107: 6000 | J107: 1979
... B113: =B112+1 -> 105 | D113: Matthews Arena | E113: Boston | F113: Massachusetts | G113: Northeastern men | H113: CAA | I113: 6000 | J113: 1910
B114: =B113+1 -> 106 | D114: Forbes Arena | E114: Atlanta | F114: Georgia | G114: Morehouse Maroon Tigers | H114: SIAC | I114: 6000 | J114: 1996[6]
B115: =B114+1 -> 107 | D115: Reese Court | E115: Cheney | F115: Washington | G115: Eastern Washington | H115: Big Sky | I115: 6000 | J115: 1981
B116: =B115+1 -> 108 | D116: Cadet Field House | E116: Colorado Springs | F116: Colorado | G116: Air Force | H116: Mountain West | I116: 5858 | J116: 1968
B117: =B116+1 -> 109 | D117: Yost Ice Arena | E117: Ann Arbor | F117: Michigan | G117: Michigan | H117: Big Ten | I117: 5800 | J117: 1923
B118: =B117+1 -> 110 | D118: Cameron Hall | E118: Lexington | F118: Virginia | G118: VMI | H118: Southern | I118: 5800 | J118: 1981
B119: =B118+1 -> 111 | D119: UNF Arena | E119: Jacksonville | F119: Florida | G119: North Florida | H119: ASUN | I119: 5800 | J119: 1993
B120: =B119+1 -> 112 | D120: Brooks Center | E120: St. Cloud | F120: Minnesota | G120: St. Cloud State men & women | H120: NCHC (men) WCHA (women) | I120: 5763 | J120: 1989
B121: =B120+1 -> 113 | D121: Tudor Fieldhouse | E121: Houston | F121: Texas | G121: Rice | H121: C-USA (The American in 2023) | I121: 5750 | J121: 1950
B122: =B121+1 -> 114 | D122: Alumni Hall | E122: Annapolis | F122: Maryland | G122: Navy | H122: Patriot | I122: 5710 | J122: 1991
B123: =B122+1 -> 115 | D123: Scheels Center | E123: Fargo | F123: North Dakota | G123: North Dakota State | H123: Summit | I123: 5700 | J123: 2016
B124: =B123+1 -> 116 | D124: Corbett Sports Center | E124: Greensboro | F124: North Carolina | G124: North Carolina A&T | H124: Big South | I124: 5700 | J124: 1978
B125: =B124+1 -> 117 | D125: Bren Events Center | E125: Irvine | F125: California | G125: UC Irvine | H125: Big West | I125: 5608 | J125: 1987
B126: =B125+1 -> 118 | D126: Carnesecca Arena | E126: Queens | F126: New York | G126: St. John's women | H126: Big East | I126: 5602 | J126: 1961
... B130: =B129+1 -> 122 | D130: James A. Rhodes Arena | E130: Akron | F130: Ohio | G130: Akron | H130: MAC | I130: 5500 | J130: 1983
B131: =B130+1 -> 123 | D131: Hytche Athletic Center | E131: Princess Anne | F131: Maryland | G131: Maryland Eastern Shore | H131: MEAC | I131: 5500 | J131: 1999[7]
B132: =B131+1 -> 124 | D132: Rafael A. Mangual Coliseum | E132: Mayagüez | F132: Puerto Rico | G132: Puerto Rico-Mayagüez Tarzans and Janes | H132: NCAA D-II Independent LAI | I132: 5500 | J132: 1974
B133: =B132+1 -> 125 | D133: Reilly Center | E133: St. Bonaventure | F133: New York | G133: St. Bonaventure | H133: Atlantic 10 | I133: 5480 | J133: 1966
B134: =B133+1 -> 126 | D134: University Arena | E134: Kalamazoo | F134: Michigan | G134: Western Michigan | H134: MAC | I134: 5421 | J134: 1957
B135: =B134+1 -> 127 | D135: The Complex | E135: Valdosta | F135: Georgia | G135: Valdosta State Blazers | H135: Gulf South | I135: 5350 | J135: 1982
B136: =B135+1 -> 128 | D136: McGuirk Arena | E136: Mount Pleasant | F136: Michigan | G136: Central Michigan | H136: MAC | I136: 5300 | J136: 1973
B137: =B136+1 -> 129 | D137: America First Event Center | E137: Cedar City | F137: Utah | G137: Southern Utah | H137: WAC | I137: 5300 | J137: 1985
B138: =B137+1 -> 130 | D138: Lantz Arena | E138: Charleston | F138: Illinois | G138: Eastern Illinois | H138: Ohio Valley | I138: 5300 | J138: 1967
B139: =B138+1 -> 131 | D139: The Sobrato Center | E139: San Francisco | F139: California | G139: San Francisco | H139: West Coast | I139: 5300 | J139: 1958
B140: =B139+1 -> 132 | D140: John M. Belk Arena | E140: Davidson | F140: North Carolina | G140: Davidson | H140: Atlantic 10 | I140: 5223 | J140: 1989
B141: =B140+1 -> 133 | D141: SECU Arena | E141: Towson | F141: Maryland | G141: Towson | H141: CAA | I141: 5200 | J141: 2013
B142: =B141+1 -> 134 | D142: Trojan Arena | E142: Troy | F142: Alabama | G142: Troy | H142: Sun Belt | I142: 5200 | J142: 2012
B143: =B142+1 -> 135 | D143: Trask Coliseum | E143: Wilmington | F143: North Carolina | G143: UNC Wilmington | H143: CAA | I143: 5200 | J143: 1977
... B150: =B149+1 -> 142 | D150: Schar Center | E150: Elon | F150: North Carolina | G150: Elon | H150: CAA | I150: 5100 | J150: 2018
B151: =B150+1 -> 143 | D151: VSU Multi-Purpose Center | E151: Ettrick | F151: Virginia | G151: Virginia State Trojans | H151: CIAA | I151: 5100 | J151: 2016[9]
B152: =B151+1 -> 144 | D152: Health and Sports Center | E152: Kearney | F152: Nebraska | G152: Nebraska–Kearney Lopers | H152: MIAA | I152: 5100 | J152: 1990[10]
B153: =B152+1 -> 145 | D153: Curb Event Center | E153: Nashville | F153: Tennessee | G153: Belmont | H153: Missouri Valley | I153: 5085 | J153: 2003
B154: =B153+1 -> 146 | D154: CBU Events Center | E154: Riverside | F154: California | G154: California Baptist | H154: WAC | I154: 5050 | J154: 2017
B155: =B154+1 -> 147 | D155: Christl Arena | E155: West Point | F155: New York | G155: Army | H155: Patriot | I155: 5043 | J155: 1985
B156: =B155+1 -> 148 | D156: Allen Arena | E156: Nashville | F156: Tennessee | G156: Lipscomb | H156: ASUN | I156: 5028 | J156: 2001
B157: =B156+1 -> 149 | D157: Compton Family Ice Arena | E157: Notre Dame | F157: Indiana | G157: Notre Dame | H157: Big Ten | I157: 5022 | J157: 2011
B158: =B157+1 -> 150 | D158: Tex Turner Arena | E158: Harrogate | F158: Tennessee | G158: Lincoln Memorial Railsplitters | H158: South Atlantic | I158: 5009 | J158: 1991
B159: =B158+1 -> 151 | D159: Harrison HPER Complex | E159: Itta Bena | F159: Mississippi | G159: Mississippi Valley State | H159: SWAC | I159: 5000 | J159: 1970[12]
B160: =B159+1 -> 152 | D160: Charles E. Smith Center | E160: Washington | F160: DC | G160: George Washington | H160: Atlantic 10 | I160: 5000 | J160: 1975
B161: =B160+1 -> 153 | D161: Edmunds Center | E161: DeLand | F161: Florida | G161: Stetson | H161: ASUN | I161: 5000 | J161: 1974
B162: =B161+1 -> 154 | D162: Bob Carpenter Center | E162: Newark | F162: Delaware | G162: Delaware | H162: CAA | I162: 5000 | J162: 1992
B163: =B162+1 -> 155 | D163: Ocean Bank Convocation Center | E163: Miami | F163: Florida | G163: FIU | H163: C-USA | I163: 5000 | J163: 1986
B164: =B163+1 -> 156 | D164: Slater Family Ice Arena | E164: Bowling Green | F164: Ohio | G164: Bowling Green | H164: CCHA | I164: 5000 | J164: 1967
B165: =B164+1 -> 157 | D165: Athletics–Recreation Center | E165: Valparaiso | F165: Indiana | G165: Valparaiso | H165: Missouri Valley | I165: 5000 | J165: 1984
B166: =B165+1 -> 158 | D166: Provident Credit Union Event Center | E166: San Jose | F166: California | G166: San Jose State | H166: Mountain West | I166: 5000 | J166: 1989
B167: =B166+1 -> 159 | D167: Kathleen and Tom Elam Center | E167: Martin | F167: Tennessee | G167: Tennessee-Martin | H167: Ohio Valley | I167: 5000 | J167: 1969
B168: =B167+1 -> 160 | D168: Mullett Arena | E168: Tempe | F168: Arizona | G168: Arizona State | H168: Independent | I168: 5000 | J168: 2022
B169: =B168+1 -> 161 | D169: Texas A&M–Commerce Field House | E169: Commerce | F169: Texas | G169: Texas A&M–Commerce | H169: Southland | I169: 5000 | J169: 1950
B170: =B169+1 -> 162 | D170: Van Noord Arena | E170: Grand Rapids | F170: Michigan | G170: Calvin | H170: MIAC | I170: 5000 | J170: 2009
B171: =B170+1 -> 163 | D171: R.L. Vaughn Center | E171: Elizabeth City | F171: North Carolina | G171: Elizabeth City State Vikings | H171: CIAC | I171: 5000 | J171: 1976[13]
B172: =B171+1 -> 164 | D172: Sawyer Center | E172: Bethany | F172: Oklahoma | G172: Southern Nazarene Crimson Storm | H172: Great American | I172: 5000 | J172: 1999
B173: =B172+1 -> 165 | D173: Alaska Airlines Center | E173: Anchorage | F173: Alaska | G173: Alaska Anchorage Seawolves | H173: GNAC | I173: 5000 | J173: 2014
B174: =B173+1 -> 166 | D174: William L. White Auditorium | E174: Emporia | F174: Kansas | G174: Emporia State Hornets | H174: MIAA | I174: 5000 | J174: 1941
B175: =B174+1 -> 167 | D175: Kovalchick Convention and Athletic Complex | E175: Indiana | F175: Pennsylvania | G175: IUP Crimson Hawks | H175: PSAC | I175: 5000 | J175: 2011
B176: =B175+1 -> 168 | D176: HPER Complex | E176: Albany | F176: Georgia | G176: Albany State Golden Rams | H176: SIAC | I176: 5000 | J176: 1997[14]
B177: =B176+1 -> 169 | D177: HPE Basketball Arena/Wildcat Arena | E177: Fort Valley | F177: Georgia | G177: Fort Valley State Wildcats | H177: SIAC | I177: 5000 | J177: N/A
B178: =B177+1 -> 170 | D178: Tiger Arena | E178: Savannah | F178: Georgia | G178: Savannah State Tigers and Lady Tigers | H178: SIAC | I178: 5000 | J178: 2000
B179: =B178+1 -> 171 | D179: Daniel "Chappie" James Center | E179: Tuskegee | F179: Alabama | G179: Tuskegee Golden Tigers | H179: SIAC | I179: 5000 | J179: 1987[16]
G181: Total Facility Capacity | I181: =SUM(I9:I179) -> 1143341
G182: Average Attendance | I182: =(0.5+0.75)/2 -> 0.625
...
